coinbase/__init__.py
coinbase/auth.py
coinbase/client.py
coinbase/response_types/__init__.py
coinbase/response_types/buy_price.py
coinbase/response_types/currency_price.py
coinbase/response_types/sell_price.py
coinbase/response_types/server_time.py
coinbase/response_types/spot_price.py
myb_coinbase_api-1.1.0.dist-info/LICENSE
myb_coinbase_api-1.1.0.dist-info/METADATA
myb_coinbase_api-1.1.0.dist-info/WHEEL
myb_coinbase_api-1.1.0.dist-info/top_level.txt
myb_coinbase_api-1.1.0.dist-info/RECORD
